moko_translate/__init__.py
moko_translate/translator.py
moko_translate-0.1.0.dist-info/METADATA
moko_translate-0.1.0.dist-info/WHEEL
moko_translate-0.1.0.dist-info/top_level.txt
moko_translate-0.1.0.dist-info/RECORD
